graph2tac/__init__.py
graph2tac/common.py
graph2tac/hash.py
graph2tac/predict.py
graph2tac/loader/__init__.py
graph2tac/loader/data_classes.py
graph2tac/loader/data_server.py
graph2tac/loader/hmodel.py
graph2tac/loader/predict_server.py
graph2tac/tfgnn/__init__.py
graph2tac/tfgnn/graph_schema.py
graph2tac/tfgnn/metrics.py
graph2tac/tfgnn/models.py
graph2tac/tfgnn/plot_predict_graphs.py
graph2tac/tfgnn/predict.py
graph2tac/tfgnn/stack_graph_tensors.py
graph2tac/tfgnn/tasks.py
graph2tac/tfgnn/train.py
graph2tac/tfgnn/train_utils.py
graph2tac-1.0.4.dist-info/LICENSE
graph2tac-1.0.4.dist-info/METADATA
graph2tac-1.0.4.dist-info/WHEEL
graph2tac-1.0.4.dist-info/entry_points.txt
graph2tac-1.0.4.dist-info/top_level.txt
graph2tac-1.0.4.dist-info/RECORD
