Metadata-Version: 2.1
Name: graph2tac
Version: 1.0.4
Summary: Train and run models which predict tactics for Coq.
Author: Lasse Blaauwbroek, Fidel I. Schaposnik Massolo, Miroslav Olšák, Vasily Pestun, Jason Rute
License: MIT
Project-URL: Homepage, https://github.com/IBM/graph2tac
Project-URL: Issues, https://github.com/IBM/graph2tac/issues
Project-URL: Repository, https://github.com/IBM/graph2tac
Classifier: Intended Audience :: Science/Research
Classifier: Programming Language :: Python :: 3 :: Only
Classifier: Programming Language :: Python :: 3
Classifier: Programming Language :: Python :: 3.9
Classifier: Programming Language :: Python :: 3.10
Classifier: Programming Language :: Python :: 3.11
Classifier: License :: OSI Approved :: MIT License
Classifier: Operating System :: POSIX :: Linux
Classifier: Operating System :: MacOS
Classifier: Topic :: Scientific/Engineering
Classifier: Topic :: Scientific/Engineering :: Mathematics
Classifier: Topic :: Scientific/Engineering :: Artificial Intelligence
Requires-Python: <3.12,>=3.9
License-File: LICENSE
Requires-Dist: keras >=2.8
Requires-Dist: tensorflow <2.13,>=2.12.0
Requires-Dist: tensorflow-gnn <0.3,>=0.2.0
Requires-Dist: protobuf <4.0
Requires-Dist: tqdm
Requires-Dist: numpy
Requires-Dist: pycapnp
Requires-Dist: psutil
Requires-Dist: pyyaml
Requires-Dist: graphviz
Requires-Dist: pytactician ==15.1
Requires-Dist: pytest
